ss_file_query/__init__.py
ss_file_query/tools/__init__.py
ss_file_query/tools/query_tool.py
ss_file_query/tools/utils.py
ss_file_query/yamls/file_query_tool.yaml
tests/__init__.py
tests/test_file_query_tool.py
ss_file_query-0.0.1.dist-info/METADATA
ss_file_query-0.0.1.dist-info/WHEEL
ss_file_query-0.0.1.dist-info/entry_points.txt
ss_file_query-0.0.1.dist-info/top_level.txt
ss_file_query-0.0.1.dist-info/RECORD
