Metadata-Version: 2.1
Name: ss-file-query
Version: 0.0.1
Summary: Semi-structured file query tool
